 [
  {
    "board_id": 1,
    "issue": [
			{
				"issue_id": 1,
				"title": "이슈1",
				"content": "이슈 내용 1",
				"deadline": "2022-05-25T09:46:00Z",
				"priority": "F",
				"created_at": "2022-05-16T00:41:36.409243Z",
				"updated_at": "2022-05-16T00:41:36.409243Z",
				"board": 1
			}
    ],
		"title": "Todo",
		"project": 1
  },
  {
		"board_id": 2,
		"issue": [
			{
				"issue_id": 2,
				"title": "이슈2",
				"content": "이슈 내용 2",
				"deadline": "2022-05-25T09:46:00Z",
				"priority": "F",
				"created_at": "2022-05-16T00:42:32.031786Z",
				"updated_at": "2022-05-16T00:42:32.031786Z",
				"board": 2
			}
		],
		"title": "In progress",
		"project": 1
  },
  {
		"board_id": 3,
		"issue": [
			{
				"issue_id": 3,
				"title": "이슈3",
				"content": "이슈 내용 3",
				"deadline": "2022-05-11T01:46:00Z",
				"priority": "M",
				"created_at": "2022-05-16T02:43:40.737922Z",
				"updated_at": "2022-05-16T02:43:40.737922Z",
				"board": 3
			}
		],
		"title": "검증",
		"project": 1
  },
  {
      "board_id": 4,
      "issue": [
          {
              "issue_id": 4,
              "title": "이슈4",
              "content": "이슈4 연습용",
              "deadline": "2022-06-09T01:50:00Z",
              "priority": "S",
              "created_at": "2022-05-16T02:44:00.436965Z",
              "updated_at": "2022-05-16T02:44:00.436965Z",
              "board": 4
          }
      ],
      "title": "완료",
      "project": 1
  }

  
]




